lzdb/__init__.py
lzdb/lzdb.py
lzdb2-1.3.0.dist-info/licenses/LICENSE
lzdb2-1.3.0.dist-info/METADATA
lzdb2-1.3.0.dist-info/WHEEL
lzdb2-1.3.0.dist-info/top_level.txt
lzdb2-1.3.0.dist-info/RECORD
