Metadata-Version: 2.4
Name: lzdb2
Version: 1.3.0
Summary: Lazy Database
Author-email: Fabien Bouleau <fabien.bouleau@gmail.com>
License-Expression: GPL-3.0-or-later
Project-URL: Homepage, https://github.com/fboule/lzdb
Project-URL: Issues, https://github.com/fboule/lzdb/issues
Keywords: lzdb2,gplv3,python
Classifier: Programming Language :: Python :: 3
Classifier: Operating System :: OS Independent
Requires-Python: >=3.8
License-File: LICENSE
Requires-Dist: pandas>=2.0
Requires-Dist: matplotlib
Requires-Dist: numpy
Requires-Dist: psycopg
Dynamic: license-file
